fuck_windsurf/__init__.py
fuck_windsurf/__main__.py
fuck_windsurf/debug.py
fuck_windsurf/i18n.py
fuck_windsurf/py.typed
fuck_windsurf/server.py
fuck_windsurf/desktop_app/__init__.py
fuck_windsurf/desktop_app/desktop_app.py
fuck_windsurf/desktop_release/__init__.py
fuck_windsurf/desktop_release/mcp-feedback-enhanced-desktop-linux
fuck_windsurf/desktop_release/mcp-feedback-enhanced-desktop-macos-arm64
fuck_windsurf/desktop_release/mcp-feedback-enhanced-desktop-macos-intel
fuck_windsurf/desktop_release/mcp-feedback-enhanced-desktop.exe
fuck_windsurf/utils/__init__.py
fuck_windsurf/utils/error_handler.py
fuck_windsurf/utils/memory_monitor.py
fuck_windsurf/utils/resource_manager.py
fuck_windsurf/web/__init__.py
fuck_windsurf/web/main.py
fuck_windsurf/web/constants/__init__.py
fuck_windsurf/web/constants/message_codes.py
fuck_windsurf/web/locales/en/translation.json
fuck_windsurf/web/locales/zh-CN/translation.json
fuck_windsurf/web/locales/zh-TW/translation.json
fuck_windsurf/web/models/__init__.py
fuck_windsurf/web/models/feedback_result.py
fuck_windsurf/web/models/feedback_session.py
fuck_windsurf/web/routes/__init__.py
fuck_windsurf/web/routes/main_routes.py
fuck_windsurf/web/static/favicon.ico
fuck_windsurf/web/static/icon-192.png
fuck_windsurf/web/static/icon.svg
fuck_windsurf/web/static/index.html
fuck_windsurf/web/static/css/audio-management.css
fuck_windsurf/web/static/css/notification-settings.css
fuck_windsurf/web/static/css/prompt-management.css
fuck_windsurf/web/static/css/session-management.css
fuck_windsurf/web/static/css/styles.css
fuck_windsurf/web/static/js/app.js
fuck_windsurf/web/static/js/i18n.js
fuck_windsurf/web/static/js/modules/connection-monitor.js
fuck_windsurf/web/static/js/modules/file-upload-manager.js
fuck_windsurf/web/static/js/modules/image-handler.js
fuck_windsurf/web/static/js/modules/logger.js
fuck_windsurf/web/static/js/modules/session-manager.js
fuck_windsurf/web/static/js/modules/settings-manager.js
fuck_windsurf-2.6.0.dist-info/METADATA
fuck_windsurf-2.6.0.dist-info/WHEEL
fuck_windsurf-2.6.0.dist-info/entry_points.txt
fuck_windsurf-2.6.0.dist-info/licenses/LICENSE
fuck_windsurf-2.6.0.dist-info/RECORD
